st_file_uploader/__init__.py
st_file_uploader/_languages.py
st_file_uploader/_version.py
st_file_uploader/frontend/.prettierrc
st_file_uploader/frontend/package-lock.json
st_file_uploader/frontend/package.json
st_file_uploader/frontend/tsconfig.json
st_file_uploader/frontend/build/asset-manifest.json
st_file_uploader/frontend/build/bootstrap.min.css
st_file_uploader/frontend/build/index.html
st_file_uploader/frontend/build/static/js/main.3e560990.js
st_file_uploader/frontend/build/static/js/main.3e560990.js.LICENSE.txt
st_file_uploader/frontend/build/static/js/main.3e560990.js.map
st_file_uploader/frontend/build/static/js/main.8503740c.js
st_file_uploader/frontend/build/static/js/main.8503740c.js.LICENSE.txt
st_file_uploader/frontend/build/static/js/main.8503740c.js.map
st_file_uploader/frontend/public/bootstrap.min.css
st_file_uploader/frontend/public/index.html
st_file_uploader/frontend/src/CustomUploader.tsx
st_file_uploader/frontend/src/index.tsx
st_file_uploader/frontend/src/react-app-env.d.ts
st_file_uploader-0.2.2.dist-info/licenses/LICENSE
st_file_uploader-0.2.2.dist-info/METADATA
st_file_uploader-0.2.2.dist-info/WHEEL
st_file_uploader-0.2.2.dist-info/top_level.txt
st_file_uploader-0.2.2.dist-info/RECORD
